bddk.py
bddk-1.1.dist-info/LICENSE.txt
bddk-1.1.dist-info/METADATA
bddk-1.1.dist-info/WHEEL
bddk-1.1.dist-info/top_level.txt
bddk-1.1.dist-info/RECORD
