Metadata-Version: 2.1
Name: bddk
Version: 1.1
Summary: Bddk Veri
Home-page: https://github.com/barbasan/bddk
Author: Ilyas Burak Hizarci
Author-email: i.burakhizarci@gmail.com
License: UNKNOWN
Platform: UNKNOWN
Classifier: Programming Language :: Python :: 3
Classifier: Programming Language :: Python :: 3.7
Classifier: Programming Language :: Python :: 3.8
Classifier: License :: OSI Approved :: MIT License
Classifier: Development Status :: 4 - Beta
Classifier: Operating System :: Microsoft :: Windows
Classifier: Operating System :: MacOS
Classifier: Operating System :: POSIX :: Linux
Classifier: Intended Audience :: Financial and Insurance Industry
Requires-Dist: pandas
Requires-Dist: openpyxl
Requires-Dist: selenium
Requires-Dist: urllib3
Requires-Dist: requests
